{
  "skippableComposables": 429,
  "restartableComposables": 475,
  "readonlyComposables": 0,
  "totalComposables": 494,
  "restartGroups": 475,
  "totalGroups": 573,
  "staticArguments": 694,
  "certainArguments": 111,
  "knownStableArguments": 4232,
  "knownUnstableArguments": 87,
  "unknownStableArguments": 90,
  "totalArguments": 4409,
  "markedStableClasses": 15,
  "inferredStableClasses": 64,
  "inferredUnstableClasses": 1,
  "inferredUncertainClasses": 0,
  "effectivelyStableClasses": 79,
  "totalClasses": 80,
  "memoizedLambdas": 504,
  "singletonLambdas": 0,
  "singletonComposableLambdas": 173,
  "composableLambdas": 278,
  "totalLambdas": 504,
  "featureFlags": {
    "StrongSkipping": true,
    "IntrinsicRemember": true,
    "OptimizeNonSkippingGroups": false,
    "PausableComposition": false
  }
}