{
 "skippableComposables": 30,
 "restartableComposables": 35,
 "readonlyComposables": 0,
 "totalComposables": 35,
 "restartGroups": 35,
 "totalGroups": 42,
 "staticArguments": 30,
 "certainArguments": 5,
 "knownStableArguments": 307,
 "knownUnstableArguments": 8,
 "unknownStableArguments": 3,
 "totalArguments": 318,
 "markedStableClasses": 0,
 "inferredStableClasses": 1,
 "inferredUnstableClasses": 1,
 "inferredUncertainClasses": 0,
 "effectivelyStableClasses": 1,
 "totalClasses": 2,
 "memoizedLambdas": 38,
 "singletonLambdas": 11,
 "singletonComposableLambdas": 4,
 "composableLambdas": 24,
 "totalLambdas": 44
}